whisper_pandas.py
whisper_pandas-0.1.dist-info/LICENSE
whisper_pandas-0.1.dist-info/METADATA
whisper_pandas-0.1.dist-info/WHEEL
whisper_pandas-0.1.dist-info/entry_points.txt
whisper_pandas-0.1.dist-info/top_level.txt
whisper_pandas-0.1.dist-info/RECORD
