Metadata-Version: 2.1
Name: whisper-pandas
Version: 0.1
Summary: WhisperDB Python Pandas Reader
Home-page: https://github.com/heidelbergcement/whisper-pandas
Author: Christoph Deil
Author-email: deil.christoph@gmail.com
License: MIT
Platform: any
Requires-Python: >=3.7
License-File: LICENSE
Requires-Dist: pandas
Requires-Dist: whisper
